pycowsay/__init__.py
pycowsay/__main__.py
pycowsay/main.py
pycowsay-0.0.0.2.data/data/share/man/man6/pycowsay.6
pycowsay-0.0.0.2.dist-info/LICENSE
pycowsay-0.0.0.2.dist-info/METADATA
pycowsay-0.0.0.2.dist-info/WHEEL
pycowsay-0.0.0.2.dist-info/entry_points.txt
pycowsay-0.0.0.2.dist-info/top_level.txt
pycowsay-0.0.0.2.dist-info/RECORD
