Metadata-Version: 2.1
Name: pycowsay
Version: 0.0.0.2
Home-page: https://github.com/cs01/pycowsay
Author: Chad Smith
Author-email: grassfedcode@gmail.com
License: License :: OSI Approved :: MIT License
Classifier: Programming Language :: Python
Requires-Python: >=3.6
License-File: LICENSE
